MANIFEST.in
README.md
setup.cfg
setup.py
bin/runpygg.py
pygg/__init__.py
pygg/pygg.py
pygg.egg-info/PKG-INFO
pygg.egg-info/SOURCES.txt
pygg.egg-info/dependency_links.txt
pygg.egg-info/requires.txt
pygg.egg-info/top_level.txt