Metadata-Version: 1.0
Name: pygg
Version: 0.1.12
Summary: ggplot2 syntax for python.  Runs R version of ggplot2 under the covers
Home-page: http://github.com/sirrice/pygg
Author: Eugene Wu
Author-email: ewu@cs.columbia.edu
License: MIT
Platform: UNKNOWN
